amdfans/__init__.py
amdfans/cli.py
amdfans/config.py
amdfans/controller.py
amdfans/logger.py
amdfans/utilities.py
amdfans-0.0.1.dist-info/DESCRIPTION.rst
amdfans-0.0.1.dist-info/METADATA
amdfans-0.0.1.dist-info/RECORD
amdfans-0.0.1.dist-info/WHEEL
amdfans-0.0.1.dist-info/entry_points.txt
amdfans-0.0.1.dist-info/metadata.json
amdfans-0.0.1.dist-info/top_level.txt
