Metadata-Version: 2.0
Name: amdfans
Version: 0.0.1
Summary: Command-line program for setting AMD GPU fan speeds
Home-page: https://github.com/jorrinpollard/amdfans
Author: Jorrin Pollard
Author-email: me@jorrinpollard.com
License: MIT
Platform: UNKNOWN
Classifier: Development Status :: 3 - Alpha
Classifier: Environment :: Console
Classifier: Intended Audience :: End Users/Desktop
Classifier: License :: OSI Approved :: MIT License
Classifier: Natural Language :: English
Classifier: Operating System :: POSIX :: Linux
Classifier: Programming Language :: Python :: 3
Requires-Dist: appdirs
Requires-Dist: click
Requires-Dist: ww
